alibabacloud_intelligentcreation20250301/__init__.py
alibabacloud_intelligentcreation20250301/client.py
alibabacloud_intelligentcreation20250301/models/__init__.py
alibabacloud_intelligentcreation20250301/models/_create_label_task_request.py
alibabacloud_intelligentcreation20250301/models/_create_label_task_response.py
alibabacloud_intelligentcreation20250301/models/_create_label_task_response_body.py
alibabacloud_intelligentcreation20250301/models/_create_oss_upload_token_request.py
alibabacloud_intelligentcreation20250301/models/_create_oss_upload_token_response.py
alibabacloud_intelligentcreation20250301/models/_create_oss_upload_token_response_body.py
alibabacloud_intelligentcreation20250301/models/_create_text_label_request.py
alibabacloud_intelligentcreation20250301/models/_create_text_label_response.py
alibabacloud_intelligentcreation20250301/models/_create_text_label_response_body.py
alibabacloud_intelligentcreation20250301/models/_get_label_task_result_request.py
alibabacloud_intelligentcreation20250301/models/_get_label_task_result_response.py
alibabacloud_intelligentcreation20250301/models/_get_label_task_result_response_body.py
alibabacloud_intelligentcreation20250301-1.0.1.dist-info/LICENSE
alibabacloud_intelligentcreation20250301-1.0.1.dist-info/METADATA
alibabacloud_intelligentcreation20250301-1.0.1.dist-info/WHEEL
alibabacloud_intelligentcreation20250301-1.0.1.dist-info/top_level.txt
alibabacloud_intelligentcreation20250301-1.0.1.dist-info/RECORD
